pyco_mongo
